azure/mgmt/agfood/__init__.py
azure/mgmt/agfood/_azure_ag_food_platform_rp_service.py
azure/mgmt/agfood/_configuration.py
azure/mgmt/agfood/_version.py
azure/mgmt/agfood/aio/__init__.py
azure/mgmt/agfood/aio/_azure_ag_food_platform_rp_service.py
azure/mgmt/agfood/aio/_configuration.py
azure/mgmt/agfood/aio/operations/__init__.py
azure/mgmt/agfood/aio/operations/_extensions_operations.py
azure/mgmt/agfood/aio/operations/_farm_beats_extensions_operations.py
azure/mgmt/agfood/aio/operations/_farm_beats_models_operations.py
azure/mgmt/agfood/aio/operations/_locations_operations.py
azure/mgmt/agfood/aio/operations/_operations.py
azure/mgmt/agfood/models/__init__.py
azure/mgmt/agfood/models/_azure_ag_food_platform_rp_service_enums.py
azure/mgmt/agfood/models/_models.py
azure/mgmt/agfood/models/_models_py3.py
azure/mgmt/agfood/operations/__init__.py
azure/mgmt/agfood/operations/_extensions_operations.py
azure/mgmt/agfood/operations/_farm_beats_extensions_operations.py
azure/mgmt/agfood/operations/_farm_beats_models_operations.py
azure/mgmt/agfood/operations/_locations_operations.py
azure/mgmt/agfood/operations/_operations.py
azure_mgmt_agfood-1.0.0b2.dist-info/LICENSE
azure_mgmt_agfood-1.0.0b2.dist-info/METADATA
azure_mgmt_agfood-1.0.0b2.dist-info/WHEEL
azure_mgmt_agfood-1.0.0b2.dist-info/top_level.txt
azure_mgmt_agfood-1.0.0b2.dist-info/RECORD
